stardicter/__init__.py
stardicter/base.py
stardicter/czech.py
stardicter/czechenglish.py
stardicter/czechgerman.py
stardicter/deaccent.py
stardicter/dictsinfo.py
stardicter/main.py
stardicter/test_base.py
stardicter/test_czech.py
stardicter/test_czechenglish.py
stardicter/test_czechgerman.py
stardicter/test_data.txt
stardicter/test_deaccent.py
stardicter/test_dictsinfo.py
stardicter/test_word.py
stardicter/utils.py
stardicter/word.py
stardicter-2.0.1.dist-info/licenses/COPYING
stardicter-2.0.1.dist-info/METADATA
stardicter-2.0.1.dist-info/WHEEL
stardicter-2.0.1.dist-info/entry_points.txt
stardicter-2.0.1.dist-info/top_level.txt
stardicter-2.0.1.dist-info/RECORD
