Metadata-Version: 2.4
Name: stardicter
Version: 2.0.1
Summary: Conversion tools from various formats to StarDict.
Author-email: Michal Čihař <michal@cihar.com>
License-Expression: GPL-3.0-or-later
Project-URL: Download, https://pypi.python.org/pypi/stardicter
Project-URL: Homepage, https://cihar.com/software/slovnik/
Keywords: stardict,dictionary
Platform: any
Classifier: Development Status :: 5 - Production/Stable
Classifier: Topic :: Internet
Classifier: Topic :: Software Development :: Libraries :: Python Modules
Classifier: Topic :: Utilities
Classifier: Operating System :: OS Independent
Classifier: Intended Audience :: Developers
Classifier: Programming Language :: Python
Classifier: Programming Language :: Python :: 3.9
Classifier: Programming Language :: Python :: 3.10
Classifier: Programming Language :: Python :: 3.11
Classifier: Programming Language :: Python :: 3.12
Classifier: Programming Language :: Python :: 3.13
Requires-Python: >=3.9
License-File: COPYING
Dynamic: license-file
